README.rst
setup.py
Hummingbird.egg-info/PKG-INFO
Hummingbird.egg-info/SOURCES.txt
Hummingbird.egg-info/dependency_links.txt
Hummingbird.egg-info/requires.txt
Hummingbird.egg-info/top_level.txt
hummingbird/__init__.py
hummingbird/objects.py
hummingbird/tests/__init__.py