Metadata-Version: 1.1
Name: Hummingbird
Version: 0.0.2
Summary: An API Wrapper for Hummingbird.me
Home-page: https://github.com/KnightHawk3/hummingbird
Author: Melody Kelly
Author-email: melody@melody.blue
License: MIT
Keywords: Hummingbird anime api wrapper
Platform: UNKNOWN
Classifier: Development Status :: 2 - Pre-Alpha
Classifier: Topic :: Utilities
Classifier: Intended Audience :: Developers
Classifier: Operating System :: OS Independent
Classifier: Programming Language :: Python :: 3
Classifier: Environment :: Console
Classifier: License :: OSI Approved :: MIT License
